.pylintrc
AUTHORS
ChangeLog
README.rst
requirements.txt
setup.cfg
setup.py
YasExampleHandlers.egg-info/PKG-INFO
YasExampleHandlers.egg-info/SOURCES.txt
YasExampleHandlers.egg-info/dependency_links.txt
YasExampleHandlers.egg-info/not-zip-safe
YasExampleHandlers.egg-info/pbr.json
YasExampleHandlers.egg-info/requires.txt
YasExampleHandlers.egg-info/top_level.txt
etc/yas/handlers/example.yml
yas_example_handlers/__init__.py
yas_example_handlers/configuration.py
yas_example_handlers/yaml_file_config.py