Metadata-Version: 1.1
Name: YasExampleHandlers
Version: 0.0.2
Summary: Just some examples
Home-page: https://github.com/schlueter/YasExampleHandlers
Author: Brandon Schlueter
Author-email: yas@schlueter.blue
License: UNKNOWN
Platform: UNKNOWN
Classifier: Environment :: Plugins
Classifier: Intended Audience :: Information Technology
Classifier: Intended Audience :: System Administrators
Classifier: License :: OSI Approved :: GNU Affero General Public License v3 or later (AGPLv3+)
Classifier: Operating System :: POSIX :: Linux
Classifier: Programming Language :: Python
Classifier: Programming Language :: Python :: 3
Classifier: Programming Language :: Python :: 3.6
Classifier: Topic :: Communications :: Chat
